{
  "version": "7",
  "dialect": "postgresql",
  "entries": [
    {
      "idx": 0,
      "version": "7",
      "when": 1776332336888,
      "tag": "0000_sticky_jane_foster",
      "breakpoints": true
    },
    {
      "idx": 1,
      "version": "7",
      "when": 1776340792047,
      "tag": "0001_overjoyed_albert_cleary",
      "breakpoints": true
    },
    {
      "idx": 2,
      "version": "7",
      "when": 1776357575020,
      "tag": "0002_blushing_butterfly",
      "breakpoints": true
    },
    {
      "idx": 3,
      "version": "7",
      "when": 1776359557361,
      "tag": "0003_polite_sprite",
      "breakpoints": true
    }
  ]
}